hgboost/__init__.py
hgboost/examples.py
hgboost/hgboost.py
hgboost/shapplot.py
hgboost-1.1.7.dist-info/licenses/LICENSE
hgboost-1.1.7.dist-info/METADATA
hgboost-1.1.7.dist-info/WHEEL
hgboost-1.1.7.dist-info/top_level.txt
hgboost-1.1.7.dist-info/RECORD
