Metadata-Version: 2.4
Name: hgboost
Version: 1.1.7
Summary: hgboost is a python package for hyperparameter optimization for xgboost, catboost and lightboost for both classification and regression tasks.
Author-email: Erdogan Taskesen <erdogant@gmail.com>
License-Expression: MIT
Project-URL: Homepage, https://erdogant.github.io/hgboost
Project-URL: Download, https://github.com/erdogant/hgboost/archive/{version}.tar.gz
Keywords: Python,machine learning,hyperparameter optimization,catboost,xgboost,lightgbm,grid search,cross-validation,classification,regression,boosting,automated machine learning,model selection,ensemble methods
Classifier: Programming Language :: Python :: 3
Classifier: Operating System :: OS Independent
Classifier: Intended Audience :: Education
Classifier: Intended Audience :: Science/Research
Classifier: Operating System :: Unix
Classifier: Operating System :: Microsoft :: Windows
Classifier: Operating System :: MacOS
Classifier: Topic :: Scientific/Engineering :: Artificial Intelligence
Requires-Python: >=3
License-File: LICENSE
Requires-Dist: datazets
Requires-Dist: pypickle
Requires-Dist: matplotlib
Requires-Dist: numpy
Requires-Dist: pandas
Requires-Dist: tqdm
Requires-Dist: hyperopt
Requires-Dist: lightgbm>=4.1.0
Requires-Dist: xgboost
Requires-Dist: classeval
Requires-Dist: treeplot
Requires-Dist: df2onehot
Requires-Dist: colourmap
Requires-Dist: seaborn
Dynamic: license-file
